{
	"application": {
		"name": "SAM 2: Segment Anything in Images and Videos",
		"authors": [
			{
				"name": "Holoscan Team",
				"affiliation": "NVIDIA"
			}
		],
		"language": "Python",
		"version": "1.0.0",
		"changelog": {
			"1.0": "Initial Release"
		},
		"holoscan_sdk": {
			"minimum_required_version": "2.0.0",
			"tested_versions": [
				"2.0.0"
			]
		},
		"platforms": [
			"x86_64",
			"aarch64"
		],
		"tags": ["Computer Vision and Perception", "Video", "Segmentation", "Visualization", "Camera"],
		"ranking": 1,
		"dependencies": {
			"SAM2": {
				"source": "https://github.com/facebookresearch/segment-anything-2",
				"version": "1.0",
				"license": "Apache-2.0"
			}
		},

		"run": {
			"command": "<holohub_app_source>/start.sh",
			"workdir": "holohub_bin"
		}
	}
}
